src/__init__.py
src/__main__.py
src/driver.py
src/sheng/__init__.py
src/sheng/ast.py
src/sheng/builtins.py
src/sheng/compile.py
src/sheng/context.py
src/sheng/exception.py
src/sheng/lex.py
src/sheng/parse.py
src/sheng/utils.py
src/sheng/ply/__init__.py
src/sheng/ply/lex.py
src/sheng/ply/yacc.py
sheng-0.1.22.dist-info/LICENSE
sheng-0.1.22.dist-info/METADATA
sheng-0.1.22.dist-info/WHEEL
sheng-0.1.22.dist-info/entry_points.txt
sheng-0.1.22.dist-info/top_level.txt
sheng-0.1.22.dist-info/RECORD
