Metadata-Version: 2.1
Name: sheng
Version: 0.1.22
Summary: The Sheng programming language: A Chinese programming language
Home-page: https://github.com/luojiahai/sheng
Author: luojiahai
Author-email: luo@jiahai.co
License: UNKNOWN
Project-URL: Bug Tracker, https://github.com/luojiahai/sheng/issues
Platform: UNKNOWN
Classifier: Programming Language :: Python :: 3.9
Classifier: License :: OSI Approved :: MIT License
Classifier: Operating System :: OS Independent
Requires-Python: >=3.9
License-File: LICENSE
